{
  "image": null,
  "is_dark_mode": true,
  "mode": "dark",
  "base16": {
    "base00": { "default": { "color": "#1a0f0f" } },
    "base01": { "default": { "color": "#2d1b1b" } },
    "base02": { "default": { "color": "#422929" } },
    "base03": { "default": { "color": "#5c3d3d" } },
    "base04": { "default": { "color": "#a67c7c" } },
    "base05": { "default": { "color": "#f7e1e1" } },
    "base06": { "default": { "color": "#fff0f0" } },
    "base07": { "default": { "color": "#ffffff" } },
    "base08": { "default": { "color": "#ff4d88" } },
    "base09": { "default": { "color": "#ff8fab" } },
    "base0a": { "default": { "color": "#f4c2c2" } },
    "base0b": { "default": { "color": "#88b04b" } },
    "base0c": { "default": { "color": "#d4f1be" } },
    "base0d": { "default": { "color": "#efb1b1" } },
    "base0e": { "default": { "color": "#ff758f" } },
    "base0f": { "default": { "color": "#3d2424" } }
  },
  "colors": {
    "background": { "default": { "color": "#1a0f0f" } },
    "primary": { "default": { "color": "#ff8fab" } },
    "secondary": { "default": { "color": "#88b04b" } },
    "tertiary": { "default": { "color": "#ff4d88" } },
    "error": { "default": { "color": "#ff1a1a" } },
    "error_container": { "default": { "color": "#422929" } },
    "inverse_on_surface": { "default": { "color": "#1a0f0f" } },
    "inverse_primary": { "default": { "color": "#ff8fab" } },
    "inverse_surface": { "default": { "color": "#f7e1e1" } },
    "on_background": { "default": { "color": "#f7e1e1" } },
    "on_error": { "default": { "color": "#ffffff" } },
    "on_error_container": { "default": { "color": "#ff1a1a" } },
    "on_primary": { "default": { "color": "#2d1b1b" } },
    "on_primary_container": { "default": { "color": "#ffffff" } },
    "on_primary_fixed": { "default": { "color": "#2d1b1b" } },
    "on_primary_fixed_variant": { "default": { "color": "#422929" } },
    "on_secondary": { "default": { "color": "#1a0f0f" } },
    "on_secondary_container": { "default": { "color": "#ffffff" } },
    "on_secondary_fixed": { "default": { "color": "#1a0f0f" } },
    "on_secondary_fixed_variant": { "default": { "color": "#422929" } },
    "on_surface": { "default": { "color": "#fff0f0" } },
    "on_surface_variant": { "default": { "color": "#f7e1e1" } },
    "on_tertiary": { "default": { "color": "#ffffff" } },
    "on_tertiary_container": { "default": { "color": "#ffffff" } },
    "on_tertiary_fixed": { "default": { "color": "#ffffff" } },
    "on_tertiary_fixed_variant": { "default": { "color": "#5c3d3d" } },
    "outline": { "default": { "color": "#5c3d3d" } },
    "outline_variant": { "default": { "color": "#422929" } },
    "primary_container": { "default": { "color": "#2d1b1b" } },
    "primary_fixed": { "default": { "color": "#ff8fab" } },
    "primary_fixed_dim": { "default": { "color": "#422929" } },
    "scrim": { "default": { "color": "#000000" } },
    "secondary_container": { "default": { "color": "#2d1b1b" } },
    "secondary_fixed": { "default": { "color": "#88b04b" } },
    "secondary_fixed_dim": { "default": { "color": "#422929" } },
    "shadow": { "default": { "color": "#000000" } },
    "source_color": { "default": { "color": "#ff8fab" } },
    "surface": { "default": { "color": "#2d1b1b" } },
    "surface_bright": { "default": { "color": "#422929" } },
    "surface_container": { "default": { "color": "#1a0f0f" } },
    "surface_container_high": { "default": { "color": "#2d1b1b" } },
    "surface_container_highest": { "default": { "color": "#422929" } },
    "surface_container_low": { "default": { "color": "#1a0f0f" } },
    "surface_container_lowest": { "default": { "color": "#0d0707" } },
    "surface_dim": { "default": { "color": "#1a0f0f" } },
    "surface_tint": { "default": { "color": "#ff8fab" } },
    "surface_variant": { "default": { "color": "#422929" } },
    "tertiary_container": { "default": { "color": "#2d1b1b" } },
    "tertiary_fixed": { "default": { "color": "#ff4d88" } },
    "tertiary_fixed_dim": { "default": { "color": "#5c3d3d" } }
  }
}
