{
  "id": "housekinokuni",
  "name": "Land of the Lustrous",
  "version": "1.0.0",
  "author": "Seu Nome",
  "description": "Prismatic gemstone and crystalline luster minimal theme",
  "dark": {
    "name": "Phosphophyllite",
    "primary": "#00f5d4",
    "primaryText": "#00382f",
    "primaryContainer": "#005044",
    "secondary": "#ffffff",
    "surface": "#121417",
    "surfaceText": "#e1f7f4",
    "surfaceVariant": "#1b1f24",
    "surfaceVariantText": "#9bf6ff",
    "surfaceTint": "#00f5d4",
    "background": "#090a0c",
    "backgroundText": "#ffffff",
    "outline": "#323942",
    "surfaceContainer": "#121417",
    "surfaceContainerHigh": "#1b1f24",
    "surfaceContainerHighest": "#262b33",
    "error": "#ff3355",
    "warning": "#ffd000",
    "info": "#00f5d4"
  },
  "light": {
    "name": "Crystalline Shore",
    "primary": "#006b5c",
    "primaryText": "#ffffff",
    "primaryContainer": "#4effdc",
    "secondary": "#1f2429",
    "surface": "#f7faf9",
    "surfaceText": "#090a0c",
    "surfaceVariant": "#e0e4e2",
    "surfaceVariantText": "#1b1f24",
    "surfaceTint": "#006b5c",
    "background": "#edf2f0",
    "backgroundText": "#090a0c",
    "outline": "#707975",
    "surfaceContainer": "#e0e4e2",
    "surfaceContainerHigh": "#d0d4d2",
    "surfaceContainerHighest": "#c0c4c2",
    "error": "#ba1a1a",
    "warning": "#6c5a00",
    "info": "#006b5c"
  },
  "sourceDir": "housekinokuni"
}
