{
  "id": "tokyonight-amoled",
  "name": "TokyoNight AMOLED",
  "version": "1.0.0",
  "author": "Seu Nome",
  "description": "A clean TokyoNight variant with pitch black backgrounds",
  "dark": {
    "name": "TokyoNight AMOLED",
    "primary": "#7aa2f7",
    "primaryText": "#000000",
    "primaryContainer": "#1f2335",
    "secondary": "#73daca",
    "surface": "#000000",
    "surfaceText": "#a9b1d6",
    "surfaceVariant": "#10101a",
    "surfaceVariantText": "#9aa5ce",
    "surfaceTint": "#7aa2f7",
    "background": "#000000",
    "backgroundText": "#a9b1d6",
    "outline": "#383e5a",
    "surfaceContainer": "#08090f",
    "surfaceContainerHigh": "#121424",
    "surfaceContainerHighest": "#1a1c31",
    "error": "#f7768e",
    "warning": "#e0af68",
    "info": "#0db9d7"
  },
  "light": {
    "name": "TokyoLight High",
    "primary": "#34548a",
    "primaryText": "#ffffff",
    "primaryContainer": "#e1e6f0",
    "secondary": "#006757",
    "surface": "#ffffff",
    "surfaceText": "#374247",
    "surfaceVariant": "#edf1f7",
    "surfaceVariantText": "#4e5a65",
    "surfaceTint": "#34548a",
    "background": "#f5f6f9",
    "backgroundText": "#374247",
    "outline": "#8c9ca8",
    "surfaceContainer": "#edf1f7",
    "surfaceContainerHigh": "#e1e6f0",
    "surfaceContainerHighest": "#d4db execution",
    "error": "#8c4351",
    "warning": "#8f5e16",
    "info": "#005a70"
  },
  "sourceDir": "tokyonight-amoled"
}
